.bzrignore
MANIFEST.in
Makefile
ez_setup.py
setup.py
alea/__init__.py
alea/die.py
alea/table.py
alea.egg-info/PKG-INFO
alea.egg-info/SOURCES.txt
alea.egg-info/dependency_links.txt
alea.egg-info/top_level.txt
alea.egg-info/zip-safe
test/__init__.py
test/scaffold.py
test/stub_die.py
test/stub_table.py
test/suite.py
test/test_die.py
test/test_table.py
