Metadata-Version: 1.0
Name: alea
Version: 0.1.2
Summary: Random generators for games
Home-page: http://cheeseshop.python.org/pypi/alea/
Author: Ben Finney
Author-email: ben+python@benfinney.id.au
License: GPL
Keywords: alea random game die dice roll table
Platform: UNKNOWN
Classifier: Development Status :: 3 - Alpha
Classifier: License :: OSI Approved :: GNU General Public License (GPL)
Classifier: Programming Language :: Python
Classifier: Topic :: Games/Entertainment
Classifier: Topic :: Games/Entertainment :: Board Games
Classifier: Operating System :: OS Independent
Classifier: Intended Audience :: Developers
